llama_index/packs/vectara_rag/__init__.py
llama_index/packs/vectara_rag/base.py
llama_index_packs_vectara_rag-0.5.1.dist-info/METADATA
llama_index_packs_vectara_rag-0.5.1.dist-info/WHEEL
llama_index_packs_vectara_rag-0.5.1.dist-info/licenses/LICENSE
llama_index_packs_vectara_rag-0.5.1.dist-info/RECORD
