Metadata-Version: 2.4
Name: llama-index-packs-vectara-rag
Version: 0.5.1
Summary: llama-index packs vectara_rag integration
Author-email: Your Name <you@example.com>
Maintainer: ofermend
License-Expression: MIT
License-File: LICENSE
Keywords: embeddings,rag,retrieval,vectara
Requires-Python: <4.0,>=3.9
Requires-Dist: llama-index-core<0.15,>=0.13.0
Requires-Dist: llama-index-indices-managed-vectara<0.6,>=0.5.0
